{
  "entities": {
    "country_fr": {
      "automatically_extensible": true, 
      "use_synonyms": true, 
      "data": [
        {
          "synonyms": [], 
          "value": "Afghanistan"
        }, 
        {
          "synonyms": [], 
          "value": "Afrique du Sud"
        }, 
        {
          "synonyms": [], 
          "value": "Albanie"
        }, 
        {
          "synonyms": [], 
          "value": "Alg\u00e9rie"
        }, 
        {
          "synonyms": [], 
          "value": "Allemagne"
        }, 
        {
          "synonyms": [], 
          "value": "Andorre"
        }, 
        {
          "synonyms": [], 
          "value": "Angola"
        }, 
        {
          "synonyms": [
            "Antigua et barduda"
          ], 
          "value": "Antigua-et-Barbuda"
        }, 
        {
          "synonyms": [], 
          "value": "Arabie saoudite"
        }, 
        {
          "synonyms": [], 
          "value": "Argentine"
        }, 
        {
          "synonyms": [], 
          "value": "Arm\u00e9nie"
        }, 
        {
          "synonyms": [], 
          "value": "Australie"
        }, 
        {
          "synonyms": [], 
          "value": "Autriche"
        }, 
        {
          "synonyms": [], 
          "value": "Azerba\u00efdjan"
        }, 
        {
          "synonyms": [], 
          "value": "Bahamas"
        }, 
        {
          "synonyms": [], 
          "value": "Bahre\u00efn"
        }, 
        {
          "synonyms": [], 
          "value": "Bangladesh"
        }, 
        {
          "synonyms": [], 
          "value": "Barbade"
        }, 
        {
          "synonyms": [], 
          "value": "Belgique"
        }, 
        {
          "synonyms": [], 
          "value": "Belize"
        }, 
        {
          "synonyms": [], 
          "value": "B\u00e9nin"
        }, 
        {
          "synonyms": [], 
          "value": "Bhoutan"
        }, 
        {
          "synonyms": [], 
          "value": "Birmanie"
        }, 
        {
          "synonyms": [], 
          "value": "Bolivie"
        }, 
        {
          "synonyms": [], 
          "value": "Bosnie-Herz\u00e9govine"
        }, 
        {
          "synonyms": [], 
          "value": "Botswana"
        }, 
        {
          "synonyms": [], 
          "value": "Br\u00e9sil"
        }, 
        {
          "synonyms": [], 
          "value": "Brunei"
        }, 
        {
          "synonyms": [], 
          "value": "Bulgarie"
        }, 
        {
          "synonyms": [], 
          "value": "Burkina Faso"
        }, 
        {
          "synonyms": [], 
          "value": "Burundi"
        }, 
        {
          "synonyms": [], 
          "value": "Cambodge"
        }, 
        {
          "synonyms": [], 
          "value": "Cameroun"
        }, 
        {
          "synonyms": [], 
          "value": "Canada"
        }, 
        {
          "synonyms": [], 
          "value": "Cap-Vert"
        }, 
        {
          "synonyms": [], 
          "value": "Chili"
        }, 
        {
          "synonyms": [], 
          "value": "Chypre"
        }, 
        {
          "synonyms": [], 
          "value": "Colombie"
        }, 
        {
          "synonyms": [], 
          "value": "Comores"
        }, 
        {
          "synonyms": [], 
          "value": "Cor\u00e9e du Nord"
        }, 
        {
          "synonyms": [
            "Cor\u00e9e"
          ], 
          "value": "Cor\u00e9e du Sud"
        }, 
        {
          "synonyms": [], 
          "value": "Costa Rica"
        }, 
        {
          "synonyms": [], 
          "value": "C\u00f4te d'Ivoire"
        }, 
        {
          "synonyms": [], 
          "value": "Croatie"
        }, 
        {
          "synonyms": [], 
          "value": "Cuba"
        }, 
        {
          "synonyms": [], 
          "value": "Djibouti"
        }, 
        {
          "synonyms": [], 
          "value": "Dominique"
        }, 
        {
          "synonyms": [], 
          "value": "\u00c9gypte"
        }, 
        {
          "synonyms": [
            "Emirats", 
            " Emirat arabes"
          ], 
          "value": "\u00c9mirats arabes unis"
        }, 
        {
          "synonyms": [], 
          "value": "\u00c9quateur"
        }, 
        {
          "synonyms": [], 
          "value": "\u00c9rythr\u00e9e"
        }, 
        {
          "synonyms": [], 
          "value": "Espagne"
        }, 
        {
          "synonyms": [], 
          "value": "Estonie"
        }, 
        {
          "synonyms": [
            "USA", 
            " etats-unis"
          ], 
          "value": "\u00c9tats-Unis"
        }, 
        {
          "synonyms": [], 
          "value": "\u00c9thiopie"
        }, 
        {
          "synonyms": [], 
          "value": "Fidji"
        }, 
        {
          "synonyms": [], 
          "value": "Finlande"
        }, 
        {
          "synonyms": [], 
          "value": "France"
        }, 
        {
          "synonyms": [], 
          "value": "Gabon"
        }, 
        {
          "synonyms": [], 
          "value": "Gambie"
        }, 
        {
          "synonyms": [], 
          "value": "G\u00e9orgie"
        }, 
        {
          "synonyms": [], 
          "value": "Ghana"
        }, 
        {
          "synonyms": [], 
          "value": "Gr\u00e8ce"
        }, 
        {
          "synonyms": [], 
          "value": "Grenade"
        }, 
        {
          "synonyms": [], 
          "value": "Guatemala"
        }, 
        {
          "synonyms": [], 
          "value": "Guin\u00e9e"
        }, 
        {
          "synonyms": [], 
          "value": "Guin\u00e9e \u00e9quatoriale"
        }, 
        {
          "synonyms": [
            "Guin\u00e9e Bissau"
          ], 
          "value": "Guin\u00e9e-Bissau"
        }, 
        {
          "synonyms": [], 
          "value": "Guyana"
        }, 
        {
          "synonyms": [
            "Haiti"
          ], 
          "value": "Ha\u00efti"
        }, 
        {
          "synonyms": [], 
          "value": "Honduras"
        }, 
        {
          "synonyms": [], 
          "value": "Hongrie"
        }, 
        {
          "synonyms": [
            "Maurice"
          ], 
          "value": "\u00eele Maurice"
        }, 
        {
          "synonyms": [
            "Marshall"
          ], 
          "value": "\u00eeles Marshall"
        }, 
        {
          "synonyms": [], 
          "value": "Inde"
        }, 
        {
          "synonyms": [], 
          "value": "Indon\u00e9sie"
        }, 
        {
          "synonyms": [], 
          "value": "Irak"
        }, 
        {
          "synonyms": [], 
          "value": "Iran"
        }, 
        {
          "synonyms": [], 
          "value": "Irlande"
        }, 
        {
          "synonyms": [], 
          "value": "Islande"
        }, 
        {
          "synonyms": [], 
          "value": "Isra\u00ebl"
        }, 
        {
          "synonyms": [], 
          "value": "Italie"
        }, 
        {
          "synonyms": [], 
          "value": "Jama\u00efque"
        }, 
        {
          "synonyms": [], 
          "value": "Japon"
        }, 
        {
          "synonyms": [], 
          "value": "Jordanie"
        }, 
        {
          "synonyms": [], 
          "value": "Kazakhstan"
        }, 
        {
          "synonyms": [], 
          "value": "Kenya"
        }, 
        {
          "synonyms": [], 
          "value": "Kirghizistan"
        }, 
        {
          "synonyms": [], 
          "value": "Kiribati"
        }, 
        {
          "synonyms": [], 
          "value": "Kowe\u00eft"
        }, 
        {
          "synonyms": [], 
          "value": "Laos"
        }, 
        {
          "synonyms": [], 
          "value": "Lesotho"
        }, 
        {
          "synonyms": [], 
          "value": "Lettonie"
        }, 
        {
          "synonyms": [], 
          "value": "Liban"
        }, 
        {
          "synonyms": [], 
          "value": "Liberia"
        }, 
        {
          "synonyms": [], 
          "value": "Libye"
        }, 
        {
          "synonyms": [], 
          "value": "Liechtenstein"
        }, 
        {
          "synonyms": [], 
          "value": "Lituanie"
        }, 
        {
          "synonyms": [], 
          "value": "Luxembourg"
        }, 
        {
          "synonyms": [], 
          "value": "Madagascar"
        }, 
        {
          "synonyms": [], 
          "value": "Malaisie"
        }, 
        {
          "synonyms": [], 
          "value": "Malawi"
        }, 
        {
          "synonyms": [], 
          "value": "Maldives"
        }, 
        {
          "synonyms": [], 
          "value": "Mali"
        }, 
        {
          "synonyms": [], 
          "value": "Malte"
        }, 
        {
          "synonyms": [], 
          "value": "Maroc"
        }, 
        {
          "synonyms": [], 
          "value": "Mauritanie"
        }, 
        {
          "synonyms": [], 
          "value": "Mexique"
        }, 
        {
          "synonyms": [], 
          "value": "Micron\u00e9sie"
        }, 
        {
          "synonyms": [
            "Moldavie"
          ], 
          "value": "R\u00e9publique de Moldavie"
        }, 
        {
          "synonyms": [], 
          "value": "Monaco"
        }, 
        {
          "synonyms": [], 
          "value": "Mongolie"
        }, 
        {
          "synonyms": [
            "Mont\u00e9n\u00e9gro"
          ], 
          "value": "Mont\u00e9n\u00e9gro"
        }, 
        {
          "synonyms": [], 
          "value": "Mozambique"
        }, 
        {
          "synonyms": [], 
          "value": "Namibie"
        }, 
        {
          "synonyms": [], 
          "value": "Nauru"
        }, 
        {
          "synonyms": [], 
          "value": "N\u00e9pal"
        }, 
        {
          "synonyms": [], 
          "value": "Nicaragua"
        }, 
        {
          "synonyms": [], 
          "value": "Niger"
        }, 
        {
          "synonyms": [], 
          "value": "Nigeria"
        }, 
        {
          "synonyms": [], 
          "value": "Norv\u00e8ge"
        }, 
        {
          "synonyms": [
            "nouvelle z\u00e9lande"
          ], 
          "value": "Nouvelle-Z\u00e9lande"
        }, 
        {
          "synonyms": [], 
          "value": "Oman"
        }, 
        {
          "synonyms": [], 
          "value": "Ouganda"
        }, 
        {
          "synonyms": [], 
          "value": "Ouzb\u00e9kistan"
        }, 
        {
          "synonyms": [], 
          "value": "Pakistan"
        }, 
        {
          "synonyms": [], 
          "value": "Palaos"
        }, 
        {
          "synonyms": [], 
          "value": "Panama"
        }, 
        {
          "synonyms": [
            "Nouvelle guin\u00e9e"
          ], 
          "value": "Papouasie-Nouvelle-Guin\u00e9e"
        }, 
        {
          "synonyms": [], 
          "value": "Paraguay"
        }, 
        {
          "synonyms": [
            "Hollande"
          ], 
          "value": "Pays-Bas"
        }, 
        {
          "synonyms": [], 
          "value": "P\u00e9rou"
        }, 
        {
          "synonyms": [], 
          "value": "Philippines"
        }, 
        {
          "synonyms": [], 
          "value": "Pologne"
        }, 
        {
          "synonyms": [], 
          "value": "Portugal"
        }, 
        {
          "synonyms": [], 
          "value": "Qatar"
        }, 
        {
          "synonyms": [
            "Centrafrique"
          ], 
          "value": "R\u00e9publique centrafricaine"
        }, 
        {
          "synonyms": [
            "Mac\u00e9doine"
          ], 
          "value": "R\u00e9publique de Mac\u00e9doine"
        }, 
        {
          "synonyms": [
            "RDC"
          ], 
          "value": "R\u00e9publique d\u00e9mocratique du Congo"
        }, 
        {
          "synonyms": [], 
          "value": "R\u00e9publique dominicaine"
        }, 
        {
          "synonyms": [
            "Congo"
          ], 
          "value": "R\u00e9publique du Congo"
        }, 
        {
          "synonyms": [
            "Chine"
          ], 
          "value": "R\u00e9publique populaire de Chine"
        }, 
        {
          "synonyms": [
            "Bi\u00e9lorussie"
          ], 
          "value": "R\u00e9publique socialiste sovi\u00e9tique de Bi\u00e9lorussie"
        }, 
        {
          "synonyms": [
            "Tch\u00e9quie"
          ], 
          "value": "R\u00e9publique tch\u00e8que"
        }, 
        {
          "synonyms": [], 
          "value": "Roumanie"
        }, 
        {
          "synonyms": [
            "Angleterre", 
            " Grande-Bretagne"
          ], 
          "value": "Royaume-Uni"
        }, 
        {
          "synonyms": [], 
          "value": "Russie"
        }, 
        {
          "synonyms": [], 
          "value": "Rwanda"
        }, 
        {
          "synonyms": [], 
          "value": "Saint-Marin"
        }, 
        {
          "synonyms": [
            "St Vincent les grenadine"
          ], 
          "value": "Saint-Vincent-et-les-Grenadines"
        }, 
        {
          "synonyms": [
            "Sainte Lucie"
          ], 
          "value": "Sainte-Lucie"
        }, 
        {
          "synonyms": [], 
          "value": "Salomon"
        }, 
        {
          "synonyms": [], 
          "value": "Salvador"
        }, 
        {
          "synonyms": [], 
          "value": "Samoa"
        }, 
        {
          "synonyms": [
            "Sao Tom\u00e9 et principe", 
            " Sao Tom\u00e9"
          ], 
          "value": "S\u00e3o Tom\u00e9 et Pr\u00edncipe"
        }, 
        {
          "synonyms": [], 
          "value": "S\u00e9n\u00e9gal"
        }, 
        {
          "synonyms": [
            "Serbie"
          ], 
          "value": "R\u00e9publique de Serbie"
        }, 
        {
          "synonyms": [], 
          "value": "Seychelles"
        }, 
        {
          "synonyms": [], 
          "value": "Sierra Leone"
        }, 
        {
          "synonyms": [], 
          "value": "Singapour"
        }, 
        {
          "synonyms": [], 
          "value": "Slovaquie"
        }, 
        {
          "synonyms": [], 
          "value": "Slov\u00e9nie"
        }, 
        {
          "synonyms": [], 
          "value": "Somalie"
        }, 
        {
          "synonyms": [], 
          "value": "Soudan"
        }, 
        {
          "synonyms": [], 
          "value": "Soudan du Sud"
        }, 
        {
          "synonyms": [], 
          "value": "Sri Lanka"
        }, 
        {
          "synonyms": [], 
          "value": "Su\u00e8de"
        }, 
        {
          "synonyms": [], 
          "value": "Suisse"
        }, 
        {
          "synonyms": [], 
          "value": "Suriname"
        }, 
        {
          "synonyms": [], 
          "value": "Swaziland"
        }, 
        {
          "synonyms": [], 
          "value": "Syrie"
        }, 
        {
          "synonyms": [], 
          "value": "Tadjikistan"
        }, 
        {
          "synonyms": [], 
          "value": "Tanzanie"
        }, 
        {
          "synonyms": [], 
          "value": "Tchad"
        }, 
        {
          "synonyms": [], 
          "value": "Tha\u00eflande"
        }, 
        {
          "synonyms": [], 
          "value": "Timor oriental"
        }, 
        {
          "synonyms": [], 
          "value": "Togo"
        }, 
        {
          "synonyms": [], 
          "value": "Tonga"
        }, 
        {
          "synonyms": [
            "Trinit\u00e9 et tobago"
          ], 
          "value": "Trinit\u00e9-et-Tobago"
        }, 
        {
          "synonyms": [], 
          "value": "Tunisie"
        }, 
        {
          "synonyms": [], 
          "value": "Turkm\u00e9nistan"
        }, 
        {
          "synonyms": [], 
          "value": "Turquie"
        }, 
        {
          "synonyms": [], 
          "value": "Tuvalu"
        }, 
        {
          "synonyms": [], 
          "value": "Ukraine"
        }, 
        {
          "synonyms": [], 
          "value": "Uruguay"
        }, 
        {
          "synonyms": [], 
          "value": "Vanuatu"
        }, 
        {
          "synonyms": [], 
          "value": "Venezuela"
        }, 
        {
          "synonyms": [
            "vietnam"
          ], 
          "value": "Vi\u00eat Nam"
        }, 
        {
          "synonyms": [], 
          "value": "Y\u00e9men"
        }, 
        {
          "synonyms": [], 
          "value": "Zambie"
        }, 
        {
          "synonyms": [], 
          "value": "Zimbabwe"
        }, 
        {
          "synonyms": [], 
          "value": "Tha\u00eflande"
        }, 
        {
          "synonyms": [], 
          "value": "Suisse"
        }, 
        {
          "synonyms": [], 
          "value": "Roumanie"
        }, 
        {
          "synonyms": [], 
          "value": "Autriche"
        }, 
        {
          "synonyms": [], 
          "value": "Gr\u00e8ce"
        }, 
        {
          "synonyms": [], 
          "value": "Luxembourg"
        }, 
        {
          "synonyms": [], 
          "value": "Hongrie"
        }, 
        {
          "synonyms": [], 
          "value": "Italie"
        }, 
        {
          "synonyms": [], 
          "value": "Arabie saoudite"
        }, 
        {
          "synonyms": [], 
          "value": "Espagne"
        }, 
        {
          "synonyms": [], 
          "value": "Canada"
        }, 
        {
          "synonyms": [], 
          "value": "Australie"
        }, 
        {
          "synonyms": [], 
          "value": "Inde"
        }, 
        {
          "synonyms": [], 
          "value": "argentine"
        }, 
        {
          "synonyms": [], 
          "value": "Br\u00e9sil"
        }, 
        {
          "synonyms": [], 
          "value": "bresil"
        }, 
        {
          "synonyms": [], 
          "value": "suede"
        }, 
        {
          "synonyms": [], 
          "value": "Gabon"
        }, 
        {
          "synonyms": [], 
          "value": "Etats-Unis"
        }, 
        {
          "synonyms": [], 
          "value": "Etats-Unis"
        }, 
        {
          "synonyms": [], 
          "value": "Allemagne"
        }, 
        {
          "synonyms": [], 
          "value": "France"
        }
      ]
    }
  }, 
  "intents": {
    "noise": {
      "utterances": [
        {
          "data": [
            {
              "text": "whaahazzaz"
            }
          ]
        }, 
        {
          "data": [
            {
              "text": "je me demande"
            }
          ]
        }, 
        {
          "data": [
            {
              "text": "blabla"
            }
          ]
        }, 
        {
          "data": [
            {
              "text": "blibli"
            }
          ]
        }, 
        {
          "data": [
            {
              "text": "et sinon ?"
            }
          ]
        }, 
        {
          "data": [
            {
              "text": "??"
            }
          ]
        }, 
        {
          "data": [
            {
              "text": "???"
            }
          ]
        }, 
        {
          "data": [
            {
              "text": "?"
            }
          ]
        }, 
        {
          "data": [
            {
              "text": "H\u00e9!"
            }
          ]
        }
      ]
    }, 
    "sayYes": {
      "utterances": [
        {
          "data": [
            {
              "text": "Allons y"
            }
          ]
        }, 
        {
          "data": [
            {
              "text": "Feu"
            }
          ]
        }, 
        {
          "data": [
            {
              "text": "Oui!"
            }
          ]
        }, 
        {
          "data": [
            {
              "text": "Oui."
            }
          ]
        }, 
        {
          "data": [
            {
              "text": "ok..."
            }
          ]
        }, 
        {
          "data": [
            {
              "text": "Ouaip"
            }
          ]
        }, 
        {
          "data": [
            {
              "text": "Ouai"
            }
          ]
        }, 
        {
          "data": [
            {
              "text": "ok, on fait comme \u00e7a"
            }
          ]
        }, 
        {
          "data": [
            {
              "text": "on fait comme \u00e7a"
            }
          ]
        }, 
        {
          "data": [
            {
              "text": "cela me va comme \u00e7a"
            }
          ]
        }, 
        {
          "data": [
            {
              "text": "cela me va"
            }
          ]
        }, 
        {
          "data": [
            {
              "text": "c'est tout bon"
            }
          ]
        }, 
        {
          "data": [
            {
              "text": "on est bon"
            }
          ]
        }, 
        {
          "data": [
            {
              "text": "oui c'est \u00e7a"
            }
          ]
        }, 
        {
          "data": [
            {
              "text": "ok cela me va"
            }
          ]
        }, 
        {
          "data": [
            {
              "text": "c'est bien \u00e7a"
            }
          ]
        }, 
        {
          "data": [
            {
              "text": "yep"
            }
          ]
        }, 
        {
          "data": [
            {
              "text": "ok"
            }
          ]
        }, 
        {
          "data": [
            {
              "text": "je suis d'accord"
            }
          ]
        }, 
        {
          "data": [
            {
              "text": "tout \u00e0 fait"
            }
          ]
        }, 
        {
          "data": [
            {
              "text": "oui d'accord"
            }
          ]
        }, 
        {
          "data": [
            {
              "text": "Yes"
            }
          ]
        }, 
        {
          "data": [
            {
              "text": "Oui"
            }
          ]
        }
      ]
    }, 
    "searchCountryCapital": {
      "utterances": [
        {
          "data": [
            {
              "text": "Sais-tu quelle est la capitale de la "
            }, 
            {
              "text": "Tha\u00eflande", 
              "entity": "country_fr", 
              "slot_name": "country"
            }, 
            {
              "text": " ?"
            }
          ]
        }, 
        {
          "data": [
            {
              "text": "S'il te plait peux-tu me donner le nom de capitale de la "
            }, 
            {
              "text": "Suisse", 
              "entity": "country_fr", 
              "slot_name": "country"
            }, 
            {
              "text": " ?"
            }
          ]
        }, 
        {
          "data": [
            {
              "text": "Donne moi la capitale de la "
            }, 
            {
              "text": "Roumanie", 
              "entity": "country_fr", 
              "slot_name": "country"
            }
          ]
        }, 
        {
          "data": [
            {
              "text": "Dites moi quelle est la capitale de l'"
            }, 
            {
              "text": "Autriche", 
              "entity": "country_fr", 
              "slot_name": "country"
            }, 
            {
              "text": " ?"
            }
          ]
        }, 
        {
          "data": [
            {
              "text": "Pouvez-vous me dire quelle est la capitale de la "
            }, 
            {
              "text": "Gr\u00e8ce", 
              "entity": "country_fr", 
              "slot_name": "country"
            }, 
            {
              "text": " ?"
            }
          ]
        }, 
        {
          "data": [
            {
              "text": "Dis moi quelle est la capitale du "
            }, 
            {
              "text": "Luxembourg", 
              "entity": "country_fr", 
              "slot_name": "country"
            }, 
            {
              "text": " ?"
            }
          ]
        }, 
        {
          "data": [
            {
              "text": "Connaissez-vous la capitale de la "
            }, 
            {
              "text": "Hongrie", 
              "entity": "country_fr", 
              "slot_name": "country"
            }, 
            {
              "text": " ?"
            }
          ]
        }, 
        {
          "data": [
            {
              "text": "C'est quoi la capitale en "
            }, 
            {
              "text": "Italie", 
              "entity": "country_fr", 
              "slot_name": "country"
            }, 
            {
              "text": " ?"
            }
          ]
        }, 
        {
          "data": [
            {
              "text": "En "
            }, 
            {
              "text": "Arabie saoudite", 
              "entity": "country_fr", 
              "slot_name": "country"
            }, 
            {
              "text": " c'est quoi la capitale ?"
            }
          ]
        }, 
        {
          "data": [
            {
              "text": "Je cherche la capitale de l'"
            }, 
            {
              "text": "Espagne", 
              "entity": "country_fr", 
              "slot_name": "country"
            }
          ]
        }, 
        {
          "data": [
            {
              "text": "Nous cherchons la capitale du "
            }, 
            {
              "text": "Canada", 
              "entity": "country_fr", 
              "slot_name": "country"
            }
          ]
        }, 
        {
          "data": [
            {
              "text": "Mais quelle est la capitale de l'"
            }, 
            {
              "text": "Australie", 
              "entity": "country_fr", 
              "slot_name": "country"
            }, 
            {
              "text": " ?"
            }
          ]
        }, 
        {
          "data": [
            {
              "text": "En "
            }, 
            {
              "text": "Inde", 
              "entity": "country_fr", 
              "slot_name": "country"
            }, 
            {
              "text": " quelle est la capitale ?"
            }
          ]
        }, 
        {
          "data": [
            {
              "text": "En "
            }, 
            {
              "text": "argentine", 
              "entity": "country_fr", 
              "slot_name": "country"
            }, 
            {
              "text": " c'est quoi la capitale ?"
            }
          ]
        }, 
        {
          "data": [
            {
              "text": "je cherche \u00e0 connaitre la capitale du "
            }, 
            {
              "text": "Br\u00e9sil", 
              "entity": "country_fr", 
              "slot_name": "country"
            }
          ]
        }, 
        {
          "data": [
            {
              "text": "Je voudrais connaitre la capitale du "
            }, 
            {
              "text": "bresil", 
              "entity": "country_fr", 
              "slot_name": "country"
            }
          ]
        }, 
        {
          "data": [
            {
              "text": "Je cherche le nom de la capitale de la "
            }, 
            {
              "text": "suede", 
              "entity": "country_fr", 
              "slot_name": "country"
            }
          ]
        }, 
        {
          "data": [
            {
              "text": "Connais-tu la capitale du "
            }, 
            {
              "text": "Gabon", 
              "entity": "country_fr", 
              "slot_name": "country"
            }, 
            {
              "text": " ?"
            }
          ]
        }, 
        {
          "data": [
            {
              "text": "Aux "
            }, 
            {
              "text": "Etats-Unis", 
              "entity": "country_fr", 
              "slot_name": "country"
            }, 
            {
              "text": " quelle est la capitale ?"
            }
          ]
        }, 
        {
          "data": [
            {
              "text": "Quelle est la capitale des "
            }, 
            {
              "text": "Etats-Unis", 
              "entity": "country_fr", 
              "slot_name": "country"
            }, 
            {
              "text": " ?"
            }
          ]
        }, 
        {
          "data": [
            {
              "text": "Et en "
            }, 
            {
              "text": "Allemagne", 
              "entity": "country_fr", 
              "slot_name": "country"
            }, 
            {
              "text": " quelle est la capitale ?"
            }
          ]
        }, 
        {
          "data": [
            {
              "text": "Quelle est la capitale de la "
            }, 
            {
              "text": "France", 
              "entity": "country_fr", 
              "slot_name": "country"
            }, 
            {
              "text": " ?"
            }
          ]
        }
      ]
    }, 
    "sayThankYou": {
      "utterances": [
        {
          "data": [
            {
              "text": "Vraiment super, merci!"
            }
          ]
        }, 
        {
          "data": [
            {
              "text": "Vraiment super!"
            }
          ]
        }, 
        {
          "data": [
            {
              "text": "merci pour votre collaboration"
            }
          ]
        }, 
        {
          "data": [
            {
              "text": "merci pour votre r\u00e9ponse rapide"
            }
          ]
        }, 
        {
          "data": [
            {
              "text": "merci pour votre aide"
            }
          ]
        }, 
        {
          "data": [
            {
              "text": "super"
            }
          ]
        }, 
        {
          "data": [
            {
              "text": "je tiens \u00e0 te remercier"
            }
          ]
        }, 
        {
          "data": [
            {
              "text": "je tiens \u00e0 vous remercier"
            }
          ]
        }, 
        {
          "data": [
            {
              "text": "thanks"
            }
          ]
        }, 
        {
          "data": [
            {
              "text": "je vous remercie infiniment"
            }
          ]
        }, 
        {
          "data": [
            {
              "text": "merci beaucoup"
            }
          ]
        }, 
        {
          "data": [
            {
              "text": "je vous remercie"
            }
          ]
        }, 
        {
          "data": [
            {
              "text": "cool, merci"
            }
          ]
        }, 
        {
          "data": [
            {
              "text": "cool, merci pour votre aide"
            }
          ]
        }, 
        {
          "data": [
            {
              "text": "super merci"
            }
          ]
        }, 
        {
          "data": [
            {
              "text": "merki"
            }
          ]
        }, 
        {
          "data": [
            {
              "text": "thk!"
            }
          ]
        }, 
        {
          "data": [
            {
              "text": "Merci!"
            }
          ]
        }
      ]
    }, 
    "sayHello": {
      "utterances": [
        {
          "data": [
            {
              "text": "Bonjour Humanoid"
            }
          ]
        }, 
        {
          "data": [
            {
              "text": "Ave, Bot!"
            }
          ]
        }, 
        {
          "data": [
            {
              "text": "Bj le bot!"
            }
          ]
        }, 
        {
          "data": [
            {
              "text": "He! Salut"
            }
          ]
        }, 
        {
          "data": [
            {
              "text": "Hello le bot!"
            }
          ]
        }, 
        {
          "data": [
            {
              "text": "Toutes mes salutations!"
            }
          ]
        }, 
        {
          "data": [
            {
              "text": "Mes salutations"
            }
          ]
        }, 
        {
          "data": [
            {
              "text": "bien le bonjour"
            }
          ]
        }, 
        {
          "data": [
            {
              "text": "Bonjour, mon ami"
            }
          ]
        }, 
        {
          "data": [
            {
              "text": "bjr"
            }
          ]
        }, 
        {
          "data": [
            {
              "text": "Coucou le bot"
            }
          ]
        }, 
        {
          "data": [
            {
              "text": "Bj le bot"
            }
          ]
        }, 
        {
          "data": [
            {
              "text": "Bonjour monsieur le bot"
            }
          ]
        }, 
        {
          "data": [
            {
              "text": "Bonjour monsieur le robot"
            }
          ]
        }, 
        {
          "data": [
            {
              "text": "allo"
            }
          ]
        }, 
        {
          "data": [
            {
              "text": "salamalec"
            }
          ]
        }, 
        {
          "data": [
            {
              "text": "kikou"
            }
          ]
        }, 
        {
          "data": [
            {
              "text": "Bonsoir"
            }
          ]
        }, 
        {
          "data": [
            {
              "text": "Coucou"
            }
          ]
        }, 
        {
          "data": [
            {
              "text": "Salutation \u00e0 vous"
            }
          ]
        }, 
        {
          "data": [
            {
              "text": "Salutation \u00e0 toi"
            }
          ]
        }, 
        {
          "data": [
            {
              "text": "Bonjour \u00e0 toi"
            }
          ]
        }, 
        {
          "data": [
            {
              "text": "Bonjour \u00e0 vous"
            }
          ]
        }, 
        {
          "data": [
            {
              "text": "Bonjour je cherche de l'aide"
            }
          ]
        }, 
        {
          "data": [
            {
              "text": "Bonjour robot"
            }
          ]
        }, 
        {
          "data": [
            {
              "text": "Bonjour vous"
            }
          ]
        }, 
        {
          "data": [
            {
              "text": "Bonjour toi"
            }
          ]
        }, 
        {
          "data": [
            {
              "text": "Salutation humain"
            }
          ]
        }, 
        {
          "data": [
            {
              "text": "Salutation!"
            }
          ]
        }, 
        {
          "data": [
            {
              "text": "Salut toi"
            }
          ]
        }, 
        {
          "data": [
            {
              "text": "Bj"
            }
          ]
        }, 
        {
          "data": [
            {
              "text": "Yo"
            }
          ]
        }, 
        {
          "data": [
            {
              "text": "Hello"
            }
          ]
        }, 
        {
          "data": [
            {
              "text": "Bonjour madame"
            }
          ]
        }, 
        {
          "data": [
            {
              "text": "Bonjour monsieur"
            }
          ]
        }, 
        {
          "data": [
            {
              "text": "Salut"
            }
          ]
        }, 
        {
          "data": [
            {
              "text": "Bonjour"
            }
          ]
        }
      ]
    }, 
    "sayGoodBye": {
      "utterances": [
        {
          "data": [
            {
              "text": "tchao bonsoir"
            }
          ]
        }, 
        {
          "data": [
            {
              "text": "\u00e0 plus tard"
            }
          ]
        }, 
        {
          "data": [
            {
              "text": "bonne journ\u00e9e"
            }
          ]
        }, 
        {
          "data": [
            {
              "text": "\u00e0 plus"
            }
          ]
        }, 
        {
          "data": [
            {
              "text": "au plaisir"
            }
          ]
        }, 
        {
          "data": [
            {
              "text": "\u00e0 la prochaine"
            }
          ]
        }, 
        {
          "data": [
            {
              "text": "adieux"
            }
          ]
        }, 
        {
          "data": [
            {
              "text": "adieu"
            }
          ]
        }, 
        {
          "data": [
            {
              "text": "\u00e0 la revoyure"
            }
          ]
        }, 
        {
          "data": [
            {
              "text": "cu"
            }
          ]
        }, 
        {
          "data": [
            {
              "text": "Byebye"
            }
          ]
        }, 
        {
          "data": [
            {
              "text": "Au revoir \u00e0 bient\u00f4t"
            }
          ]
        }, 
        {
          "data": [
            {
              "text": "A bient\u00f4t"
            }
          ]
        }, 
        {
          "data": [
            {
              "text": "a+"
            }
          ]
        }, 
        {
          "data": [
            {
              "text": "A+"
            }
          ]
        }, 
        {
          "data": [
            {
              "text": "Ciao"
            }
          ]
        }, 
        {
          "data": [
            {
              "text": "Tchao"
            }
          ]
        }, 
        {
          "data": [
            {
              "text": "Bye"
            }
          ]
        }, 
        {
          "data": [
            {
              "text": "Au revoir"
            }
          ]
        }
      ]
    }, 
    "sayNo": {
      "utterances": [
        {
          "data": [
            {
              "text": "noooo!"
            }
          ]
        }, 
        {
          "data": [
            {
              "text": "nan pas \u00e7a"
            }
          ]
        }, 
        {
          "data": [
            {
              "text": "pfeu non"
            }
          ]
        }, 
        {
          "data": [
            {
              "text": "non pas \u00e7a"
            }
          ]
        }, 
        {
          "data": [
            {
              "text": "surtout pas, non"
            }
          ]
        }, 
        {
          "data": [
            {
              "text": "J'ai chang\u00e9 d'avis"
            }
          ]
        }, 
        {
          "data": [
            {
              "text": "Non j'ai chang\u00e9 d'avis"
            }
          ]
        }, 
        {
          "data": [
            {
              "text": "Je ne veux pas"
            }
          ]
        }, 
        {
          "data": [
            {
              "text": "Surtout pas"
            }
          ]
        }, 
        {
          "data": [
            {
              "text": "Non.."
            }
          ]
        }, 
        {
          "data": [
            {
              "text": "Nan...."
            }
          ]
        }, 
        {
          "data": [
            {
              "text": "Nan"
            }
          ]
        }, 
        {
          "data": [
            {
              "text": "N\u00e9"
            }
          ]
        }, 
        {
          "data": [
            {
              "text": "Non pas d'accord"
            }
          ]
        }, 
        {
          "data": [
            {
              "text": "Attend, non"
            }
          ]
        }, 
        {
          "data": [
            {
              "text": "Non je ne veux pas"
            }
          ]
        }, 
        {
          "data": [
            {
              "text": "Non pas ainsi"
            }
          ]
        }, 
        {
          "data": [
            {
              "text": "Nope"
            }
          ]
        }, 
        {
          "data": [
            {
              "text": "No"
            }
          ]
        }, 
        {
          "data": [
            {
              "text": "Non pas du tout"
            }
          ]
        }, 
        {
          "data": [
            {
              "text": "Non"
            }
          ]
        }
      ]
    }
  }, 
  "language": "fr"
}
